[
  {
    "name": "PEQ21FD5-",
    "weight": 220,
    "code": "OPSW475F89",
    "image": "my-image1.jpg"
  },
  {
    "name": "OPQSOO334",
    "weight": 130,
    "code": "HYE881",
    "image": "my-image2.jpg"
  },
  {
    "name": "HJS_E783-",
    "weight": 170,
    "code": "IU0933_23",
    "image": "my-image3.jpg"
  },
  {
    "name": "SADXZ_34I83",
    "weight": 230,
    "code": "FF65_23",
    "image": "my-image4.jpg"
  },
  {
    "name": "JDFGK843_65",
    "weight": 80,
    "code": "44ED34_TT",
    "image": "my-image5.jpg"
  },
  {
    "name": "904G_4225F",
    "weight": 150,
    "code": "KDL849",
    "image": "my-image6.jpg"
  },
  {
    "name": "THJD93-72",
    "weight": 120,
    "code": "DKLIJK423",
    "image": "my-image7.jpg"
  },
  {
    "name": "DFYI44_8-23",
    "weight": 290,
    "code": "PSWWK78",
    "image": "my-image8.jpg"
  },
  {
    "name": "LKAWE-RR5",
    "weight": 50,
    "code": "HGRY90_",
    "image": "my-image9.jpg"
  },
  {
    "name": "HJS536_22-GH",
    "weight": 96,
    "code": "VBCDE5339",
    "image": "my-image10.jpg"
  }
]